{
  "id": "2170671",
  "name": "no name",
  "font_family": "iconfont",
  "css_prefix_text": "icon-",
  "description": "",
  "glyphs": [
    {
      "icon_id": "169949",
      "name": "标签",
      "font_class": "biaoqian",
      "unicode": "e6a9",
      "unicode_decimal": 59049
    },
    {
      "icon_id": "1272707",
      "name": "实心",
      "font_class": "heart-br",
      "unicode": "e644",
      "unicode_decimal": 58948
    },
    {
      "icon_id": "730360",
      "name": "警告",
      "font_class": "hj1",
      "unicode": "e692",
      "unicode_decimal": 59026
    },
    {
      "icon_id": "2742655",
      "name": "时间",
      "font_class": "shijian",
      "unicode": "e675",
      "unicode_decimal": 58997
    },
    {
      "icon_id": "3427871",
      "name": "浏览量",
      "font_class": "icon-",
      "unicode": "e627",
      "unicode_decimal": 58919
    },
    {
      "icon_id": "15223948",
      "name": "留言",
      "font_class": "liuyan",
      "unicode": "e600",
      "unicode_decimal": 58880
    }
  ]
}
